pyshtransform/__init__.py
pyshtransform/legendre.py
pyshtransform/py.typed
pyshtransform/wavelet.py
pyshtransform/folding/__init__.py
pyshtransform/folding/coefficients.py
pyshtransform/folding/core.py
pyshtransform/folding/transformation.py
pyshtransform/full_grid/__init__.py
pyshtransform/full_grid/core.py
pyshtransform/full_grid/grid.py
pyshtransform/full_grid/transformation.py
pyshtransform-1.1.1.dist-info/METADATA
pyshtransform-1.1.1.dist-info/WHEEL
pyshtransform-1.1.1.dist-info/licenses/LICENSE
pyshtransform-1.1.1.dist-info/RECORD
