Metadata-Version: 2.4
Name: pyshtransform
Version: 1.1.1
Summary: Spherical harmonics transformation in Python
Project-URL: Issues, https://github.com/aFarchi/pyshtransform/issues
Project-URL: Source, https://github.com/aFarchi/pyshtransform
Author-email: Alban Farchi <alban.farchi@ecmwf.int>
License-File: LICENSE
Keywords: spherical harmonics
Classifier: Intended Audience :: Science/Research
Classifier: License :: OSI Approved :: MIT License
Classifier: Operating System :: OS Independent
Classifier: Programming Language :: Python
Classifier: Programming Language :: Python :: 3
Classifier: Programming Language :: Python :: 3 :: Only
Classifier: Topic :: Scientific/Engineering
Requires-Python: >=3.11
Requires-Dist: numpy
Requires-Dist: scipy
Requires-Dist: xarray
Provides-Extra: dev
Requires-Dist: dask; extra == 'dev'
Requires-Dist: h5netcdf; extra == 'dev'
Requires-Dist: ipykernel; extra == 'dev'
Requires-Dist: mypy; extra == 'dev'
Requires-Dist: pytest; extra == 'dev'
Requires-Dist: rich; extra == 'dev'
Requires-Dist: ruff; extra == 'dev'
Requires-Dist: scipy-stubs; extra == 'dev'
